MANIFEST.in
README.rst
requirements-tests.txt
requirements.txt
setup.cfg
setup.py
django_super_favicon.egg-info/PKG-INFO
django_super_favicon.egg-info/SOURCES.txt
django_super_favicon.egg-info/dependency_links.txt
django_super_favicon.egg-info/requires.txt
django_super_favicon.egg-info/top_level.txt
favicon/__init__.py
favicon/admin.py
favicon/apps.py
favicon/models.py
favicon/settings.py
favicon/utils.py
favicon/views.py
favicon/management/__init__.py
favicon/management/commands/__init__.py
favicon/management/commands/delete_favicon.py
favicon/management/commands/generate_favicon.py
favicon/migrations/__init__.py
favicon/templates/favicon/favicon.html
favicon/templates/favicon/ieconfig.xml
favicon/templatetags/__init__.py
favicon/templatetags/favicon.py
favicon/tests/__init__.py
favicon/tests/logo.png
favicon/tests/settings.py
favicon/tests/test_command.py
favicon/tests/test_templatetags.py
favicon/tests/test_utils.py
favicon/tests/utils.py