Metadata-Version: 1.1
Name: django-super-favicon
Version: 0.6.1
Summary: 
